metabase_api/__init__.py
metabase_api/exceptions.py
metabase_api/metabase_api.py
metabase_api_python/__init__.py
metabase_api_python/exceptions.py
metabase_api_python/metabase_api.py
metabase_api_python-0.0.7.dist-info/METADATA
metabase_api_python-0.0.7.dist-info/WHEEL
metabase_api_python-0.0.7.dist-info/top_level.txt
metabase_api_python-0.0.7.dist-info/RECORD
